postgres_copy/__init__.py
sqlalchemy_postgres_copy-0.5.0.dist-info/DESCRIPTION.rst
sqlalchemy_postgres_copy-0.5.0.dist-info/METADATA
sqlalchemy_postgres_copy-0.5.0.dist-info/RECORD
sqlalchemy_postgres_copy-0.5.0.dist-info/WHEEL
sqlalchemy_postgres_copy-0.5.0.dist-info/metadata.json
sqlalchemy_postgres_copy-0.5.0.dist-info/top_level.txt
