Metadata-Version: 1.1
Name: sqlalchemy-postgres-copy
Version: 0.5.0
Summary: Utilities for using PostgreSQL COPY with SQLAlchemy
Home-page: https://github.com/jmcarp/sqlalchemy-postgres-copy
Author: Joshua Carp
Author-email: jm.carp@gmail.com
License: Copyright 2016 Joshua Carp
